typed_api_response/__init__.py
typed_api_response/builders.py
typed_api_response/errors.py
typed_api_response/response.py
typed_api_response/schemas.py
typed_api_response-1.0.0.dist-info/licenses/LICENSE
typed_api_response-1.0.0.dist-info/METADATA
typed_api_response-1.0.0.dist-info/WHEEL
typed_api_response-1.0.0.dist-info/top_level.txt
typed_api_response-1.0.0.dist-info/RECORD
