Metadata-Version: 2.4
Name: typed-api-response
Version: 1.0.0
Summary: Type-safe, extensible, strictly validated API response system for Python apps
Author-email: Michael Pearce <firstflush@protonmail.com>
License: MIT License
Project-URL: Homepage, https://github.com/firstflush/typed-api-response
Project-URL: Repository, https://github.com/firstflush/typed-api-response
Project-URL: Issues, https://github.com/firstflush/typed-api-response/issues
Keywords: api,response,wrapper,pydantic,typescript,typed,validation,http,fastapi,django,ninja
Classifier: Development Status :: 4 - Beta
Classifier: Intended Audience :: Developers
Classifier: License :: OSI Approved :: MIT License
Classifier: Programming Language :: Python :: 3.10
Classifier: Programming Language :: Python :: 3.11
Classifier: Programming Language :: Python :: 3.12
Classifier: Typing :: Typed
Classifier: Framework :: FastAPI
Classifier: Framework :: Django
Classifier: Topic :: Software Development :: Libraries :: Application Frameworks
Requires-Python: >=3.10
License-File: LICENSE
Requires-Dist: pydantic>=2.0.0
Provides-Extra: dev
Requires-Dist: pytest>=7.0; extra == "dev"
Requires-Dist: mypy>=1.0; extra == "dev"
Requires-Dist: build; extra == "dev"
Requires-Dist: twine; extra == "dev"
Dynamic: license-file
